gilp/__init__.py
gilp/_constants.py
gilp/_geometry.py
gilp/_graphic.py
gilp/examples.py
gilp/simplex.py
gilp/visualize.py
gilp/tests/__init__.py
gilp/tests/test_geometry.py
gilp/tests/test_graphic.py
gilp/tests/test_simplex.py
gilp/tests/test_visualize.py
gilp-2.1.0.dist-info/LICENSE
gilp-2.1.0.dist-info/METADATA
gilp-2.1.0.dist-info/WHEEL
gilp-2.1.0.dist-info/top_level.txt
gilp-2.1.0.dist-info/RECORD
