Metadata-Version: 2.1
Name: gilp
Version: 2.1.0
Summary: A Python package for visualizing the geometry of linear programs.
Home-page: https://github.com/engri-1101/gilp.git
Author: Henry Robbins
Author-email: hw.robbins@gmail.com
License: Creative Commons Attribution-NonCommercial-ShareAlike 4.0. https://creativecommons.org/licenses/by-nc-sa/4.0/
Classifier: Programming Language :: Python :: 3.5
Classifier: Programming Language :: Python :: 3.6
Classifier: Programming Language :: Python :: 3.7
Classifier: Programming Language :: Python :: 3.8
Classifier: Operating System :: OS Independent
Requires-Python: >=3.5
License-File: LICENSE
Requires-Dist: numpy (>=1.19)
Requires-Dist: networkx (>=2.0)
Requires-Dist: typing (>=3.7)
Requires-Dist: scipy (>=1.3)
Requires-Dist: plotly (>=5)
Provides-Extra: dev
Requires-Dist: pytest (>=5) ; extra == 'dev'
Requires-Dist: mock (>=3) ; extra == 'dev'
Requires-Dist: coverage (>=4.5) ; extra == 'dev'
Requires-Dist: tox (>=3) ; extra == 'dev'
Requires-Dist: sphinx (>=5) ; extra == 'dev'
Requires-Dist: sphinx-rtd-theme (>=1) ; extra == 'dev'
Requires-Dist: sphinx-copybutton (>=0.5) ; extra == 'dev'
